odoo/addons/report_qr/README.rst
odoo/addons/report_qr/__init__.py
odoo/addons/report_qr/__manifest__.py
odoo/addons/report_qr/controllers/__init__.py
odoo/addons/report_qr/controllers/qr.py
odoo/addons/report_qr/i18n/ca.po
odoo/addons/report_qr/i18n/it.po
odoo/addons/report_qr/i18n/report_qr.pot
odoo/addons/report_qr/models/__init__.py
odoo/addons/report_qr/models/ir_actions_report.py
odoo/addons/report_qr/readme/CONTRIBUTORS.md
odoo/addons/report_qr/readme/DESCRIPTION.md
odoo/addons/report_qr/readme/USAGE.md
odoo/addons/report_qr/static/description/icon.png
odoo/addons/report_qr/static/description/index.html
odoo/addons/report_qr/static/description/new_qr.png
odoo/addons/report_qr/static/description/old_qr.png
odoo/addons/report_qr/tests/__init__.py
odoo/addons/report_qr/tests/test_report_qr.py
odoo_addon_report_qr-18.0.1.0.0.2.dist-info/METADATA
odoo_addon_report_qr-18.0.1.0.0.2.dist-info/WHEEL
odoo_addon_report_qr-18.0.1.0.0.2.dist-info/top_level.txt
odoo_addon_report_qr-18.0.1.0.0.2.dist-info/RECORD
